microtorch/__init__.py
microtorch-0.1.1.dist-info/METADATA
microtorch-0.1.1.dist-info/WHEEL
microtorch-0.1.1.dist-info/RECORD
