Metadata-Version: 2.1
Name: microtorch
Version: 0.1.1
Summary: 
Author: mustafabozkaya
Author-email: mustafaegebozkaya555@hotmail.com
Requires-Python: >=3.9,<4.0
Classifier: Programming Language :: Python :: 3
Classifier: Programming Language :: Python :: 3.9
Classifier: Programming Language :: Python :: 3.10
Classifier: Programming Language :: Python :: 3.11
Requires-Dist: numpy (>=1.25.1,<2.0.0)
Requires-Dist: requests (>=2.31.0,<3.0.0)
Requires-Dist: torch (>=2.0.1,<3.0.0)
